LICENCE
MANIFEST.in
README.md
requirements.txt
setup.py
cumulus_message_adapter.egg-info/PKG-INFO
cumulus_message_adapter.egg-info/SOURCES.txt
cumulus_message_adapter.egg-info/dependency_links.txt
cumulus_message_adapter.egg-info/requires.txt
cumulus_message_adapter.egg-info/top_level.txt
message_adapter/__init__.py
message_adapter/aws.py
message_adapter/cumulus_message.py
message_adapter/error.py
message_adapter/message_adapter.py
message_adapter/util.py
message_adapter/version.py
tests/test-module.py
tests/test-program.py