Metadata-Version: 2.4
Name: cumulus-message-adapter
Version: 2.0.5
Summary: A command-line interface for preparing and outputting Cumulus Messages for Cumulus Tasks
Home-page: https://github.com/nasa/cumulus-message-adapter
Author: Cumulus Authors
Author-email: info@developmentseed.org
Keywords: nasa cumulus message adapter
Classifier: Intended Audience :: Developers
Classifier: Topic :: Software Development :: Build Tools
Classifier: Programming Language :: Python :: 3.12
Requires-Python: ~=3.12
License-File: LICENCE
Requires-Dist: jsonpath-ng~=1.4
Requires-Dist: jsonschema==4.17.3
Requires-Dist: boto3~=1.40.29
Dynamic: author
Dynamic: author-email
Dynamic: classifier
Dynamic: description
Dynamic: home-page
Dynamic: keywords
Dynamic: license-file
Dynamic: requires-dist
Dynamic: requires-python
Dynamic: summary
